azfuncfastapi/__init__.py
azfuncfastapi/web.py
azfuncfastapi-0.2.1.dist-info/METADATA
azfuncfastapi-0.2.1.dist-info/WHEEL
azfuncfastapi-0.2.1.dist-info/top_level.txt
azfuncfastapi-0.2.1.dist-info/RECORD
